<?xml version="1.0"?>
<odoo>

  <record model='ir.ui.view' id='passage_form'>
    <field name="name">passage_form</field>
    <field name="model">passage</field>
    <field name="arch" type="xml">
      <form string="Passage">
        <group>
          <field name="text"/>
        </group>
      </form>
    </field>
  </record>

  <record model='ir.ui.view' id='passage_tree'>
    <field name="name">passage_tree</field>
    <field name="model">passage</field>
    <field name="arch" type="xml">
      <tree string="Passages">
          <field name="sequence" widget="handle"/>
          <field name="text"/>
      </tree>
    </field>
  </record>

</odoo>